[
  {
    "fechaRegistro": "02/01/2026 21:39:39",
    "fechaReserva": "2026-01-06",
    "nombre": "benjamin Riveros ",
    "correo": "benjamin4riveros@gmail.com",
    "telefono": "956130912",
    "telefono2": "956130912",
    "horaPresentacion": "01:30",
    "centroEvento": "Avenida Macul Alto, La Florida, Región Metropolitana de Santiago 8240000, Chile",
    "destinoFinal": "San Miguel, Región Metropolitana de Santiago, Chile",
    "paradasAdicionales": "",
    "numParadas": 0,
    "numeroPersonas": "2",
    "marcaModelo": "ford ",
    "tipoTransmision": "automatico",
    "patente": "FJDG47",
    "seguro": "si",
    "distanciaKm": "12.67",
    "duracionMin": 27,
    "costoBase": 31990,
    "costoFinal": 28791,
    "codigoDescuento": "123",
    "descuentoAplicado": 3199
  },
  {
    "fechaRegistro": "02/01/2026 22:04:48",
    "fechaReserva": "2026-01-08",
    "nombre": "benjamin Riveros ",
    "correo": "benjamin4riveros@gmail.com",
    "telefono": "956130912",
    "telefono2": "956130912",
    "horaPresentacion": "00:30",
    "centroEvento": "La Fragua Oriente, Peñalolén, Región Metropolitana de Santiago 7910000, Chile",
    "destinoFinal": "La Fragua, Peñalolén, Región Metropolitana de Santiago 7910000, Chile",
    "paradasAdicionales": "",
    "numParadas": 0,
    "numeroPersonas": "2",
    "marcaModelo": "ford ",
    "tipoTransmision": "automatico",
    "patente": "FJDG47",
    "seguro": "si",
    "distanciaKm": "0.12",
    "duracionMin": "",
    "costoBase": 24990,
    "costoFinal": 22491,
    "codigoDescuento": "123",
    "descuentoAplicado": 2499
  },
  {
    "fechaRegistro": "02/01/2026 22:06:33",
    "fechaReserva": "2026-01-08",
    "nombre": "benjamin Riveros ",
    "correo": "benjamin4riveros@gmail.com",
    "telefono": "956130912",
    "telefono2": "956130912",
    "horaPresentacion": "05:00",
    "centroEvento": "La Fragua Oriente, Peñalolén, Región Metropolitana de Santiago 7910000, Chile",
    "destinoFinal": "La Fragua, Peñalolén, Región Metropolitana de Santiago 7910000, Chile",
    "paradasAdicionales": "",
    "numParadas": 0,
    "numeroPersonas": "2",
    "marcaModelo": "ford ",
    "tipoTransmision": "mecanico",
    "patente": "FJDG47",
    "seguro": "si",
    "distanciaKm": "0.12",
    "duracionMin": "",
    "costoBase": 24990,
    "costoFinal": 22491,
    "codigoDescuento": "123",
    "descuentoAplicado": 2499
  },
  {
    "fechaRegistro": "02/01/2026 22:08:56",
    "fechaReserva": "2026-01-21",
    "nombre": "benjamin Riveros ",
    "correo": "benjamin4riveros@gmail.com",
    "telefono": "956130912",
    "telefono2": "956130912",
    "horaPresentacion": "02:30",
    "centroEvento": "La Fragua Oriente, Peñalolén, Región Metropolitana de Santiago 7910000, Chile",
    "destinoFinal": "La Fragua, Peñalolén, Región Metropolitana de Santiago 7910000, Chile",
    "paradasAdicionales": "",
    "numParadas": 0,
    "numeroPersonas": "2",
    "marcaModelo": "ford ",
    "tipoTransmision": "automatico",
    "patente": "FJDG47",
    "seguro": "si",
    "distanciaKm": "0.12",
    "duracionMin": "",
    "costoBase": 24990,
    "costoFinal": 22491,
    "codigoDescuento": "123",
    "descuentoAplicado": 2499
  },
  {
    "fechaRegistro": "02/01/2026 22:11:05",
    "fechaReserva": "2026-01-21",
    "nombre": "benjamin Riveros ",
    "correo": "benjamin4riveros@gmail.com",
    "telefono": "956130912",
    "telefono2": "956130912",
    "horaPresentacion": "02:00",
    "centroEvento": "La Fragua Oriente, Peñalolén, Región Metropolitana de Santiago 7910000, Chile",
    "destinoFinal": "La Fragua, Peñalolén, Región Metropolitana de Santiago 7910000, Chile",
    "paradasAdicionales": "",
    "numParadas": 0,
    "numeroPersonas": "2",
    "marcaModelo": "ford ",
    "tipoTransmision": "automatico",
    "patente": "FJDG47",
    "seguro": "si",
    "distanciaKm": "0.12",
    "duracionMin": "",
    "costoBase": 24990,
    "costoFinal": 22491,
    "codigoDescuento": "123",
    "descuentoAplicado": 2499
  },
  {
    "fechaRegistro": "02/01/2026 22:12:28",
    "fechaReserva": "2026-01-03",
    "nombre": "benjamin Riveros ",
    "correo": "benjamin4riveros@gmail.com",
    "telefono": "956130912",
    "telefono2": "956061185",
    "horaPresentacion": "22:30",
    "centroEvento": "La Fragua Oriente, Peñalolén, Región Metropolitana de Santiago 7910000, Chile",
    "destinoFinal": "La Fragua, Peñalolén, Región Metropolitana de Santiago 7910000, Chile",
    "paradasAdicionales": "",
    "numParadas": 0,
    "numeroPersonas": "2",
    "marcaModelo": "ford ",
    "tipoTransmision": "mecanico",
    "patente": "FJDG47",
    "seguro": "no",
    "distanciaKm": "0.12",
    "duracionMin": "",
    "costoBase": 24990,
    "costoFinal": 22491,
    "codigoDescuento": "123",
    "descuentoAplicado": 2499
  },
  {
    "fechaRegistro": "02/01/2026 22:15:10",
    "fechaReserva": "2026-01-24",
    "nombre": "benjamin Riveros ",
    "correo": "benjamin4riveros@gmail.com",
    "telefono": "956130912",
    "telefono2": "956130912",
    "horaPresentacion": "02:30",
    "centroEvento": "La Fragua Oriente, Peñalolén, Región Metropolitana de Santiago 7910000, Chile",
    "destinoFinal": "La Fragua, Peñalolén, Región Metropolitana de Santiago 7910000, Chile",
    "paradasAdicionales": "",
    "numParadas": 0,
    "numeroPersonas": "2",
    "marcaModelo": "ford ",
    "tipoTransmision": "automatico",
    "patente": "FJDG47",
    "seguro": "si",
    "distanciaKm": "0.12",
    "duracionMin": "",
    "costoBase": 24990,
    "costoFinal": 22491,
    "codigoDescuento": "123",
    "descuentoAplicado": 2499
  },
  {
    "fechaRegistro": "02/01/2026 22:15:40",
    "fechaReserva": "2026-01-30",
    "nombre": "benjamin Riveros ",
    "correo": "benjamin4riveros@gmail.com",
    "telefono": "956130912",
    "telefono2": "956130912",
    "horaPresentacion": "23:30",
    "centroEvento": "La Fragua Oriente, Peñalolén, Región Metropolitana de Santiago 7910000, Chile",
    "destinoFinal": "La Fragua, Peñalolén, Región Metropolitana de Santiago 7910000, Chile",
    "paradasAdicionales": "",
    "numParadas": 0,
    "numeroPersonas": "2",
    "marcaModelo": "ford ",
    "tipoTransmision": "automatico",
    "patente": "FJDG47",
    "seguro": "si",
    "distanciaKm": "0.12",
    "duracionMin": "",
    "costoBase": 24990,
    "costoFinal": 22491,
    "codigoDescuento": "123",
    "descuentoAplicado": 2499
  },
  {
    "fechaRegistro": "02/01/2026 22:17:21",
    "fechaReserva": "2026-01-23",
    "nombre": "benjamin Riveros ",
    "correo": "benjamin4riveros@gmail.com",
    "telefono": "956130912",
    "telefono2": "956130912",
    "horaPresentacion": "23:00",
    "centroEvento": "La Fragua Oriente, Peñalolén, Región Metropolitana de Santiago 7910000, Chile",
    "destinoFinal": "La Fragua, Peñalolén, Región Metropolitana de Santiago 7910000, Chile",
    "paradasAdicionales": "",
    "numParadas": 0,
    "numeroPersonas": "2",
    "marcaModelo": "ford ",
    "tipoTransmision": "automatico",
    "patente": "FJDG47",
    "seguro": "si",
    "distanciaKm": "0.12",
    "duracionMin": "",
    "costoBase": 24990,
    "costoFinal": 22491,
    "codigoDescuento": "123",
    "descuentoAplicado": 2499
  },
  {
    "fechaRegistro": "02/01/2026 22:52:25",
    "fechaReserva": "2026-01-23",
    "nombre": "benjamin Riveros ",
    "correo": "benjamin4riveros@gmail.com",
    "telefono": "956130912",
    "telefono2": "956130912",
    "horaPresentacion": "00:00",
    "centroEvento": "Avenida Macul Alto, La Florida, Región Metropolitana de Santiago 8240000, Chile",
    "destinoFinal": "San Miguel, Región Metropolitana de Santiago, Chile",
    "paradasAdicionales": "",
    "numParadas": 0,
    "numeroPersonas": "2",
    "marcaModelo": "ford ",
    "tipoTransmision": "automatico",
    "patente": "FJDG47",
    "seguro": "si",
    "distanciaKm": "12.67",
    "duracionMin": 26,
    "costoBase": 31990,
    "costoFinal": 28791,
    "codigoDescuento": "123",
    "descuentoAplicado": 3199
  },
  {
    "fechaRegistro": "02/01/2026 22:55:04",
    "fechaReserva": "2026-01-31",
    "nombre": "benjamin Riveros ",
    "correo": "benjamin4riveros@gmail.com",
    "telefono": "956130912",
    "telefono2": "956061185",
    "horaPresentacion": "00:30",
    "centroEvento": "Avenida Macul Alto, La Florida, Región Metropolitana de Santiago 8240000, Chile",
    "destinoFinal": "San Miguel, Región Metropolitana de Santiago, Chile",
    "paradasAdicionales": "",
    "numParadas": 0,
    "numeroPersonas": "2",
    "marcaModelo": "ford ",
    "tipoTransmision": "automatico",
    "patente": "FJDG47",
    "seguro": "si",
    "distanciaKm": "12.67",
    "duracionMin": 26,
    "costoBase": 31990,
    "costoFinal": 28791,
    "codigoDescuento": "123",
    "descuentoAplicado": 3199
  }
]